astronbs/__init__.py
astronbs/_version.py
astronbs/handlers.py
astronbs/labextension/build_log.json
astronbs/labextension/package.json
astronbs/labextension/schemas/astronbs/package.json.orig
astronbs/labextension/schemas/astronbs/plugin.json
astronbs/labextension/static/lib_index_js.9c75156769b24082bfee.js
astronbs/labextension/static/lib_index_js.9c75156769b24082bfee.js.map
astronbs/labextension/static/remoteEntry.5eecd389a561e113cb67.js
astronbs/labextension/static/remoteEntry.5eecd389a561e113cb67.js.map
astronbs/labextension/static/style.js
astronbs/labextension/static/style_index_js.94a97f6a085dab231cd2.js
astronbs/labextension/static/style_index_js.94a97f6a085dab231cd2.js.map
astronbs/labextension/static/vendors-node_modules_css-loader_dist_runtime_api_js-node_modules_css-loader_dist_runtime_cssW-72eba1.c2ee182126dd1ccabd88.js
astronbs/labextension/static/vendors-node_modules_css-loader_dist_runtime_api_js-node_modules_css-loader_dist_runtime_cssW-72eba1.c2ee182126dd1ccabd88.js.map
astronbs/notebooks/__init__.py
astronbs/notebooks/color-mixer-template.ipynb
astronbs/notebooks/folder-viewer-template.ipynb
astronbs/notebooks/interactive-image-viewer.ipynb
astronbs/notebooks/light-image-combo-template.ipynb
astronbs/notebooks/quick-color-template.ipynb
astronbs/notebooks/reduction-template.ipynb
astronbs/notebooks/reprojection_template.ipynb
astronbs/tests/__init__.py
astronbs/tests/test_handlers.py
astronbs-0.14.0.data/data/etc/jupyter/jupyter_notebook_config.d/astronbs.json
astronbs-0.14.0.data/data/etc/jupyter/jupyter_server_config.d/astronbs.json
astronbs-0.14.0.data/data/share/jupyter/labextensions/astronbs/build_log.json
astronbs-0.14.0.data/data/share/jupyter/labextensions/astronbs/package.json
astronbs-0.14.0.data/data/share/jupyter/labextensions/astronbs/schemas/astronbs/package.json.orig
astronbs-0.14.0.data/data/share/jupyter/labextensions/astronbs/schemas/astronbs/plugin.json
astronbs-0.14.0.dist-info/METADATA
astronbs-0.14.0.dist-info/WHEEL
astronbs-0.14.0.dist-info/licenses/LICENSE
astronbs-0.14.0.dist-info/RECORD
