Metadata-Version: 2.1
Name: astronbs
Version: 0.14.0
Summary: JupyterLab extension to place template notebooks in t current directory
Project-URL: Homepage, https://github.com/gmwcraig/astronbs
Project-URL: Bug Tracker, https://github.com/gmwcraig/astronbs/issues
Project-URL: Repository, https://github.com/gmwcraig/astronbs.git
Author-email: Matt Craig <mattwcraig@gmail.com>
License: BSD 3-Clause License
License-File: LICENSE
Classifier: Framework :: Jupyter
Classifier: Framework :: Jupyter :: JupyterLab
Classifier: Framework :: Jupyter :: JupyterLab :: 3
Classifier: Framework :: Jupyter :: JupyterLab :: Extensions
Classifier: Framework :: Jupyter :: JupyterLab :: Extensions :: Prebuilt
Classifier: License :: OSI Approved :: BSD License
Classifier: Programming Language :: Python
Classifier: Programming Language :: Python :: 3
Classifier: Programming Language :: Python :: 3.7
Classifier: Programming Language :: Python :: 3.8
Classifier: Programming Language :: Python :: 3.9
Classifier: Programming Language :: Python :: 3.10
Requires-Python: >=3.7
Requires-Dist: jupyter-server<2,>=1.6
Provides-Extra: test
Requires-Dist: coverage; extra == 'test'
Requires-Dist: pytest; extra == 'test'
Requires-Dist: pytest-asyncio; extra == 'test'
Requires-Dist: pytest-cov; extra == 'test'
Requires-Dist: pytest-tornasync; extra == 'test'
